{
    "clearMocks": true,
    "coverageDirectory": "coverage",
    "collectCoverage": true,
    "globals": {
        "ts-jest": {
            "tsConfig": "tsconfig.json"
        },
        "window": {}
    },
    "moduleFileExtensions": ["js", "jsx", "ts", "tsx"],
    "testEnvironment": "node",
    "testMatch": ["**/src/**/*.spec.+(ts|tsx|js|jsx)", "**/tests/**/*.+(ts|tsx|js|jsx)"],
    "transform": {
        "^.+\\.(ts|tsx|js|jsx)$": "ts-jest"
    },
    "setupFiles": ["jest-localstorage-mock"],
    "preset": "ts-jest/presets/js-with-ts"
}
